main.py
xml_parser/__init__.py
xml_parser/main.py
xml_parser/parser_xml.py
xml_parser/utils.py
pyxmlparser-0.1.6.1.dist-info/LICENSE.rst
pyxmlparser-0.1.6.1.dist-info/METADATA
pyxmlparser-0.1.6.1.dist-info/WHEEL
pyxmlparser-0.1.6.1.dist-info/entry_points.txt
pyxmlparser-0.1.6.1.dist-info/top_level.txt
pyxmlparser-0.1.6.1.dist-info/RECORD
